README.rst
setup.py
timetrack/__init__.py
timetrack/constants.py
timetrack/utils.py
timetrack.egg-info/PKG-INFO
timetrack.egg-info/SOURCES.txt
timetrack.egg-info/dependency_links.txt
timetrack.egg-info/entry_points.txt
timetrack.egg-info/requires.txt
timetrack.egg-info/top_level.txt