Metadata-Version: 1.1
Name: timetrack
Version: 1.0.4
Summary: Command-line program to track your time
Home-page: https://github.com/hypothesist/timetrack
Author: Adhityaa Chandrasekar
Author-email: c.adhityaa@gmail.com
License: MIT
Keywords: time track timetrack productivity user monitor
Platform: UNKNOWN
Classifier: Development Status :: 5 - Production/Stable
Classifier: Intended Audience :: End Users/Desktop
Classifier: Topic :: Utilities
Classifier: License :: OSI Approved :: MIT License
Classifier: Programming Language :: Python :: 2
Classifier: Programming Language :: Python :: 2.6
Classifier: Programming Language :: Python :: 2.7
Classifier: Programming Language :: Python :: 3
Classifier: Programming Language :: Python :: 3.2
Classifier: Programming Language :: Python :: 3.3
Classifier: Programming Language :: Python :: 3.4
Classifier: Programming Language :: Python :: 3.5
Classifier: Operating System :: OS Independent
